coursepy/__init__.py
coursepy/all_functions.py
coursepy-1.0.1.dist-info/LICENSE.txt
coursepy-1.0.1.dist-info/METADATA
coursepy-1.0.1.dist-info/WHEEL
coursepy-1.0.1.dist-info/top_level.txt
coursepy-1.0.1.dist-info/RECORD
