Metadata-Version: 2.1
Name: coursepy
Version: 1.0.1
Summary: A course organizer that lets students map their college courses
Home-page: https://github.com/Le-Pro/CSCI354_Project_Group3
Author: Hrishav Sapkota, Sameer Acharya, Victor Iyke-Osuji
Author-email: hrishav.sapkota@bison.howard.edu, sameer.acharya@bison.howard.edu, victor.iykeosuji@bison.howard.edu
License: MIT
License-File: LICENSE.txt
